[
    {
        "id": 1,
        "name": "Cory Wong Stratocaster®",
        "price": "195.770",
        "category": "main-top",
        "clasificacion": "GUITARRAS",
        "tipo": "ELECTRICAS",
        "description": "La Noventa Stratocaster® es una máquina de tonos autorizada, con pastillas Noventa de bobina simple, controles de tono y volumen maestro y un puente Strat rígido, su llamativa buena apariencia se combina con la mordida de rango medio, agudos nítidos y graves suaves de las pastillas Noventa.",
        "image": "guitarra-1.jpg"
    },
    {
        "id": 2,
        "name": "Noventa Stratocaster®",
        "price": "245.230",
        "category": "main-top",
        "clasificacion": "GUITARRAS",
        "tipo": "ELECTRICAS",
        "description": "Guitarra",
        "image": "guitarra-2.jpg"
    },
    {
        "id": 3,
        "name": "Noventa Stratocaster®",
        "price": "245.230",
        "category": "main-top",
        "clasificacion": "GUITARRAS",
        "tipo": "ELECTRICAS",
        "description": "Guitarra",
        "image": "guitarra-2.jpg"
    },
    {
        "id": 4,
        "name": "Noventa Stratocaster®",
        "price": "245.230",
        "category": "main-top",
        "clasificacion": "GUITARRAS",
        "tipo": "ELECTRICAS",
        "description": "Guitarra",
        "image": "guitarra-2.jpg"
    },
    {
        "id": 5,
        "name": "Micro Pedal Mooer Drive Mki",
        "price": "9819",
        "category": "main-bottom",
        "clasificacion": "ACCESORIOS",
        "tipo": "PEDALES",
        "description": "",
        "image": "pedal-1.jpg"
    },
    {
        "id": 6,
        "name": "Pedal De Efecto Mooer",
        "price": "10959",
        "category": "main-bottom",
        "clasificacion": "ACCESORIOS",
        "tipo": "PEDALES",
        "description": "",
        "image": "pedal-2.jpg"
    },
    {
        "id": 7,
        "name": "Microfono Condenser Samson",
        "price": "25.861",
        "category": "main-bottom",
        "clasificacion": "MICROFONOS",
        "tipo": "DE MANO",
        "description": "",
        "image": "mic-1.jpg"
    },
    {
        "id": 8,
        "name": "Microfono Corbatero",
        "price": "18602",
        "category": "main-bottom",
        "clasificacion": "MICROFONOS",
        "tipo": "DE SOPORTE",
        "description": "",
        "image": "mic-2.jpg"
    }
]